seleniumWebUi/USelenium.py
seleniumWebUi/__init__.py
seleniumwebui-1.0.5.dist-info/LICENSE
seleniumwebui-1.0.5.dist-info/METADATA
seleniumwebui-1.0.5.dist-info/WHEEL
seleniumwebui-1.0.5.dist-info/top_level.txt
seleniumwebui-1.0.5.dist-info/RECORD
