Metadata-Version: 2.1
Name: seleniumwebui
Version: 1.0.5
Summary: selenium-web-ui-test-tool, need pywin32 for selenium3
Home-page: UNKNOWN
Author: perilong
Author-email: 357858088@qq.com
License: UNKNOWN
Platform: UNKNOWN
License-File: LICENSE
Requires-Dist: selenium (==3.141.0)
Requires-Dist: pyperclip (==1.8.2)
Requires-Dist: pywin32
